compose.db2-0.2.0.1-nspkg.pth
compose/db2/__init__.py
compose/db2/bucket.py
compose/db2/configuration.py
compose/db2/db2.py
compose/db2/debroni.py
compose/db2/formation.py
compose/db2/liteusers.py
compose/db2/users.py
compose/db2/resources/bootstrap.sh
compose/db2/resources/configure_set.sh
compose/db2/resources/conn5.sp
compose/db2/resources/custom_db.cfg
compose/db2/resources/custom_dbm.cfg
compose/db2/resources/custom_registry.cfg
compose/db2/resources/db2cli.sql
compose/db2/resources/db2mon.db.logst.sql
compose/db2/resources/db2set.sh
compose/db2/resources/db2u-config-var.cfg
compose/db2/resources/detect_db2_vrmf_change.sh
compose/db2/resources/etc_profile-NEBULA.cfg
compose/db2/resources/fgac_ddl.sql
compose/db2/resources/fgac_grant_ddl.sql
compose/db2/resources/hadr_configure.sh
compose/db2/resources/hasetup.yml
compose/db2/resources/init.sql
compose/db2/resources/initialize.sh
compose/db2/resources/keystore_update_driver.sh
compose/db2/resources/parameters.ini
compose/db2/resources/prihasetup.sql
compose/db2/resources/restore.clp
compose/db2/resources/sbyhasetup.sql
compose/db2/resources/sp.sql
compose/db2/resources/update_db.sh
compose/db2/resources/update_db2_ks.sh
compose/db2/resources/update_instance.sh
compose/db2/resources/upgrade_instance.sh
compose/db2/resources/users.json
compose/db2/utils/__init__.py
compose/db2/utils/backup.py
compose/db2/utils/cloudUtils.py
compose/db2/utils/db2rc.py
compose/db2/utils/db2utils.py
compose/db2/utils/dbKV.py
compose/db2/utils/hadr.py
compose/db2/utils/restore.py
compose/db2/utils/setup_utils.py
compose/db2/utils/sqlUtils.py
compose/db2/utils/util_funcs.py
compose/measures/__init__.py
compose/measures/db2/__init__.py
compose/measures/db2/activity.py
compose/measures/db2/replication.py
compose/tests/__init__.py
compose/tests/test_configuration.py
compose/tests/test_converge_settings.py
compose/tests/test_debroni_client.py
compose/tests/test_users.py
compose/tests/mocks/__init__.py
compose.db2-0.2.0.1.dist-info/METADATA
compose.db2-0.2.0.1.dist-info/WHEEL
compose.db2-0.2.0.1.dist-info/entry_points.txt
compose.db2-0.2.0.1.dist-info/namespace_packages.txt
compose.db2-0.2.0.1.dist-info/top_level.txt
compose.db2-0.2.0.1.dist-info/RECORD
