Metadata-Version: 2.1
Name: compose.db2
Version: 0.2.0.1
Summary: compose db2 management library
Home-page: UNKNOWN
Author: Pandu Mutyala
Author-email: pmutyala@ca.ibm.com
License: UNKNOWN
Platform: UNKNOWN
Requires-Dist: bitmath
Requires-Dist: boto3 (>=1.17.98)
Requires-Dist: cdb (==6.0.0)
Requires-Dist: debroni-client (==0.0.23.8)
Requires-Dist: dnspython (==2.1)
Requires-Dist: ibm-cos-sdk
Requires-Dist: ibm-db (==3.0.4.2)
Requires-Dist: jinja2 (>=2.10)
Requires-Dist: kubernetes (==17.17.0)
Requires-Dist: prometheus-client (>=0.11)
Requires-Dist: python-etcd
Requires-Dist: requests (>=2.26)
Requires-Dist: s3cmd
Requires-Dist: urllib3 (>=1.26.4)
Provides-Extra: dev
Requires-Dist: ipdb (==0.10.3) ; extra == 'dev'
Requires-Dist: pylint ; extra == 'dev'
Requires-Dist: yapf ; extra == 'dev'
Provides-Extra: tests
Requires-Dist: bitmath ; extra == 'tests'
Requires-Dist: mock (==2.0.0) ; extra == 'tests'
Requires-Dist: moto (==1.3.14) ; extra == 'tests'
Requires-Dist: pluggy (>=0.7.0) ; extra == 'tests'
Requires-Dist: pytest-cov (==2.6.1) ; extra == 'tests'
Requires-Dist: pytest (==4.3.1) ; extra == 'tests'
Requires-Dist: tox (==3.5.3) ; extra == 'tests'
